README.md
setup.py
json_kvs/__init__.py
json_kvs/json_kvs.py
json_kvs.egg-info/PKG-INFO
json_kvs.egg-info/SOURCES.txt
json_kvs.egg-info/dependency_links.txt
json_kvs.egg-info/top_level.txt