Metadata-Version: 2.1
Name: json-kvs
Version: 0.1
Summary: .json file based key/value storage
Home-page: https://github.com/mlubkin/json_kvs
Author: mlubkin
License: MIT
Keywords: cache key value file json
Platform: UNKNOWN
